meu_tabplot_lib/__init__.py
meu_tabplot_lib/binning.py
antonior_tabplot_pkg-0.1.8.dist-info/LICENSE
antonior_tabplot_pkg-0.1.8.dist-info/METADATA
antonior_tabplot_pkg-0.1.8.dist-info/WHEEL
antonior_tabplot_pkg-0.1.8.dist-info/RECORD
